darbiadev_ups/__init__.py
darbiadev_ups/helpers.py
darbiadev_ups/ups_services.py
darbiadev_ups-0.8.0.dist-info/METADATA
darbiadev_ups-0.8.0.dist-info/WHEEL
darbiadev_ups-0.8.0.dist-info/licenses/LICENSE
darbiadev_ups-0.8.0.dist-info/RECORD
